cmr_metadata_validator/__init__.py
cmr_metadata_validator/api_utils.py
cmr_metadata_validator/config.py
cmr_metadata_validator/data_processing.py
cmr_metadata_validator/file_operations.py
cmr_metadata_validator/get_gkr.py
cmr_metadata_validator/main.py
cmr_metadata_validator/validation.py
cmr_metadata_validator-0.1.3.dist-info/WHEEL
cmr_metadata_validator-0.1.3.dist-info/entry_points.txt
cmr_metadata_validator-0.1.3.dist-info/METADATA
cmr_metadata_validator-0.1.3.dist-info/RECORD
