Metadata-Version: 2.3
Name: cmr-metadata-validator
Version: 0.1.3
Summary: CMR Metadata Validation scripts for NASA Earth Science collections
Author: Ed Olivares
Author-email: Ed Olivares <34591886+eudoroolivares2016@users.noreply.github.com>
Requires-Dist: requests>=2.32.5
Requires-Python: >=3.13
